lexos/__init__.py
lexos/constants.py
lexos/exceptions.py
lexos/util.py
lexos/cluster/__init__.py
lexos/cluster/bootstrap_consensus.py
lexos/cluster/clustermap.py
lexos/cluster/dendrogram.py
lexos/cluster/plotly_dendrogram.py
lexos/cluster/sync_script.py
lexos/cluster/kmeans/__init__.py
lexos/cluster/kmeans/kmeans.py
lexos/corpus/__init__.py
lexos/corpus/corpus.py
lexos/corpus/corpus_analysis_report.py
lexos/corpus/corpus_stats.py
lexos/corpus/record.py
lexos/corpus/utils.py
lexos/corpus/sqlite/__init__.py
lexos/corpus/sqlite/database.py
lexos/corpus/sqlite/integration.py
lexos/cutter/__init__.py
lexos/cutter/spacy_attrs.py
lexos/cutter/text_cutter.py
lexos/cutter/token_cutter.py
lexos/dtm/__init__.py
lexos/filter/__init__.py
lexos/filter/filters.py
lexos/io/__init__.py
lexos/io/base_loader.py
lexos/io/data_loader.py
lexos/io/loader.py
lexos/io/parallel_loader.py
lexos/kwic/__init__.py
lexos/milestones/__init__.py
lexos/milestones/span_milestones.py
lexos/milestones/string_milestones.py
lexos/milestones/token_milestones.py
lexos/milestones/util.py
lexos/rolling_windows/__init__.py
lexos/rolling_windows/calculators/__init__.py
lexos/rolling_windows/calculators/averages.py
lexos/rolling_windows/calculators/base_calculator.py
lexos/rolling_windows/calculators/counts.py
lexos/rolling_windows/calculators/ratios.py
lexos/rolling_windows/plotters/__init__.py
lexos/rolling_windows/plotters/base_plotter.py
lexos/rolling_windows/plotters/plotly_plotter.py
lexos/rolling_windows/plotters/simple_plotter.py
lexos/scrubber/__init__.py
lexos/scrubber/normalize.py
lexos/scrubber/pipeline.py
lexos/scrubber/registry.py
lexos/scrubber/remove.py
lexos/scrubber/replace.py
lexos/scrubber/resources.py
lexos/scrubber/scrubber.py
lexos/scrubber/tags.py
lexos/scrubber/utils.py
lexos/tokenizer/__init__.py
lexos/tokenizer/ngrams.py
lexos/tokenizer/whitespace_counter.py
lexos/topic_modeling/__init__.py
lexos/topic_modeling/dfr_browser2/__init__.py
lexos-0.1.0b31.dist-info/METADATA
lexos-0.1.0b31.dist-info/WHEEL
lexos-0.1.0b31.dist-info/licenses/LICENSE
lexos-0.1.0b31.dist-info/RECORD
