Metadata-Version: 2.4
Name: lexos
Version: 0.1.0b31
Summary: A Python library that reproduces and extends text analysis tools from the Lexos web app. Designed for entry-level students and researchers in the Humanities, with language-agnostic support for historical and under-resourced languages.
Author-email: Scott Kleinman <scott.kleinman@csun.edu>
License-Expression: MIT
License-File: LICENSE
Requires-Python: >=3.12
Requires-Dist: biopython>=1.85
Requires-Dist: bs4>=0.0.2
Requires-Dist: chardet>=5.2.0
Requires-Dist: cytoolz>=1.0.1
Requires-Dist: dotenv>=0.9.9
Requires-Dist: fastcluster>=1.3.0
Requires-Dist: html-to-markdown>=2.8.3
Requires-Dist: ipykernel>=6.29.5
Requires-Dist: ipywidgets>=8.1.6
Requires-Dist: javaobj-py3>=0.4.4
Requires-Dist: kaleido>=1.0.0
Requires-Dist: matplotlib>=3.10.0
Requires-Dist: msgpack>=1.1.0
Requires-Dist: natsort>=8.4.0
Requires-Dist: nbformat>=5.10.4
Requires-Dist: pandas>=2.2.3
Requires-Dist: plotly<7.0.0,>=6.2.0
Requires-Dist: puremagic>=2.0.0b2
Requires-Dist: pydantic-extra-types>=2.10.2
Requires-Dist: pydantic>=2.10.4
Requires-Dist: pypdf>=5.1.0
Requires-Dist: python-docx>=1.1.2
Requires-Dist: rich>=13.9.4
Requires-Dist: ruff>=0.11.12
Requires-Dist: scipy>=1.15.1
Requires-Dist: seaborn>=0.13.2
Requires-Dist: smart-open>=7.1.0
Requires-Dist: sniffio>=1.3.1
Requires-Dist: spacy>=3.8.3
Requires-Dist: sqlalchemy>=2.0.44
Requires-Dist: srsly>=2.5.0
Requires-Dist: textacy>=0.13.0
Requires-Dist: wordcloud>=1.9.4
